bw_semver/__init__.py
bw_semver/__main__.py
bw_semver-0.0.2.dist-info/METADATA
bw_semver-0.0.2.dist-info/WHEEL
bw_semver-0.0.2.dist-info/entry_points.txt
bw_semver-0.0.2.dist-info/top_level.txt
bw_semver-0.0.2.dist-info/RECORD
