Metadata-Version: 2.1
Name: bw-semver
Version: 0.0.2
Requires-Dist: pypi-simple
